setup.py
src/metasheller.egg-info/PKG-INFO
src/metasheller.egg-info/SOURCES.txt
src/metasheller.egg-info/dependency_links.txt
src/metasheller.egg-info/requires.txt
src/metasheller.egg-info/top_level.txt
src/metashells/__init__.py
src/metashells/seashells.py
src/metashells/simulation.py