Metadata-Version: 2.1
Name: metasheller
Version: 0.1.1
Requires-Dist: scanpy
Requires-Dist: numpy
Requires-Dist: pandas
Requires-Dist: SEACells
Requires-Dist: enlighten
